sincfold/__init__.py
sincfold/_version.py
sincfold/dataset.py
sincfold/embeddings.py
sincfold/metrics.py
sincfold/model.py
sincfold/parser.py
sincfold/utils.py
sincfold/tools/RNAstructure/Readme.md
sincfold/tools/RNAstructure/ct2dot
sincfold/tools/RNAstructure/draw
sincfold/tools/RNAstructure/data_tables/rna.specification.dat
sincfold/tools/varna/Readme.md
sincfold/tools/varna/VARNAv3-93.jar
sincfold-0.16.2.dist-info/METADATA
sincfold-0.16.2.dist-info/WHEEL
sincfold-0.16.2.dist-info/entry_points.txt
sincfold-0.16.2.dist-info/licenses/LICENSE
sincfold-0.16.2.dist-info/RECORD
