Metadata-Version: 2.3
Name: sincfold
Version: 0.16.2
Summary: An end-to-end method to predict RNA secondary structure based on deep learning
Project-URL: Homepage, https://github.com/sinc-lab/sincfold
Project-URL: Bug Tracker, https://github.com/sinc-lab/sincfold/issues
Author-email: Leandro Bugnon <lbugnon@sinc.unl.edu.ar>
License-File: LICENSE
Classifier: License :: OSI Approved :: MIT License
Classifier: Operating System :: OS Independent
Classifier: Programming Language :: Python :: 3
Requires-Python: >=3.9
Requires-Dist: grakel==0.1.10
Requires-Dist: numpy==1.24.2
Requires-Dist: pandas==2.0.2
Requires-Dist: scikit-learn==1.2.1
Requires-Dist: torch==2.1
Requires-Dist: tqdm==4.64.1
